{
  "source": "recorded_during_training",
  "metric": "evaluation_loss",
  "metric_label": "Held-out MSE loss",
  "step_label": "Training updates",
  "loss_name": "mse",
  "points": [
    {
      "step": 1,
      "loss": 0.08904211941789623,
      "samples_seen": 256
    },
    {
      "step": 2,
      "loss": 0.08892990418027322,
      "samples_seen": 512
    },
    {
      "step": 4,
      "loss": 0.08833870324456639,
      "samples_seen": 1024
    },
    {
      "step": 8,
      "loss": 0.08617461769448816,
      "samples_seen": 2048
    },
    {
      "step": 16,
      "loss": 0.06059269921586766,
      "samples_seen": 4096
    },
    {
      "step": 32,
      "loss": 0.03572869443497432,
      "samples_seen": 8192
    },
    {
      "step": 64,
      "loss": 0.028733381596923242,
      "samples_seen": 16384
    },
    {
      "step": 128,
      "loss": 0.02417852789230234,
      "samples_seen": 32768
    },
    {
      "step": 256,
      "loss": 0.02182810827582935,
      "samples_seen": 65536
    },
    {
      "step": 512,
      "loss": 0.020556576473665968,
      "samples_seen": 131072
    },
    {
      "step": 1024,
      "loss": 0.019596163170817665,
      "samples_seen": 262144
    },
    {
      "step": 2048,
      "loss": 0.019583355685221553,
      "samples_seen": 524288
    },
    {
      "step": 4096,
      "loss": 0.01909471276108399,
      "samples_seen": 1048576
    },
    {
      "step": 8192,
      "loss": 0.01863767746788504,
      "samples_seen": 2097152
    },
    {
      "step": 16384,
      "loss": 0.018464886933687794,
      "samples_seen": 4194304
    },
    {
      "step": 32768,
      "loss": 0.018287740407456076,
      "samples_seen": 8388608
    },
    {
      "step": 65536,
      "loss": 0.018447749753410365,
      "samples_seen": 16777216
    },
    {
      "step": 131072,
      "loss": 0.017784690767347035,
      "samples_seen": 33554432
    },
    {
      "step": 262144,
      "loss": 0.017461988468619308,
      "samples_seen": 67108864
    }
  ],
  "best_step": 262144,
  "best_loss": 0.017461988468619308,
  "final_step": 262144,
  "final_loss": 0.017461988468619308
}
